{
  "flower": "ALL",
  "hasHoneycomb": true,
  "maxTimeInHive": 600,
  "ColorData": {
    "isBeeColored": true,
    "primaryColor": "#ffffff",
    "secondaryColor": "#ffffff",
    "primaryLayerTexture": "stones/stone_bee",
    "secondaryLayerTexture": "stones/stone_bee_secondary",
    "honeycombColor": "#888888"
  },
  "MutationData": {
    "hasMutation": false
  },
  "CentrifugeData": {
    "hasCentrifugeOutput": true,
    "mainOutput": "minecraft:stone"
  },
  "SpawnData": {
    "canSpawnInWorld": true,
    "biomeWhitelist": "tag:OVERWORLD",
    "biomeBlacklist": "tag:ocean"
  },
  "BreedData": {
    "isBreedable": true
  },
  "TraitData": {
    "hasTraits": true
  }
}